{
"type": "FeatureCollection",
"name": "office",
"crs": { "type": "name", "properties": { "name": "urn:ogc:def:crs:OGC:1.3:CRS84" } },
"features": [
{ "type": "Feature", "properties": { "building_type": "office_courier", "osm_id": "N2929585252", "lat": 40.6278079, "lon": -8.6470402, "archetype": "Working" }, "geometry": { "type": "Point", "coordinates": [ -8.6470402, 40.6278079 ] } },
{ "type": "Feature", "properties": { "building_type": "office_newspaper", "osm_id": "N11711397549", "lat": 40.6423617, "lon": -8.6486764, "archetype": "Working" }, "geometry": { "type": "Point", "coordinates": [ -8.6486764, 40.6423617 ] } },
{ "type": "Feature", "properties": { "building_type": "office_security", "osm_id": "N11818747680", "lat": 40.6815901, "lon": -8.5997834, "archetype": "Working" }, "geometry": { "type": "Point", "coordinates": [ -8.5997834, 40.6815901 ] } }
]
}
