{
"type": "FeatureCollection",
"name": "craft",
"crs": { "type": "name", "properties": { "name": "urn:ogc:def:crs:OGC:1.3:CRS84" } },
"features": [
{ "type": "Feature", "properties": { "building_type": "craft_hvac", "osm_id": "N2206346981", "lat": 58.3588572, "lon": 26.6728327, "archetype": "Salariat" }, "geometry": { "type": "Point", "coordinates": [ 26.6728327, 58.3588572 ] } },
{ "type": "Feature", "properties": { "building_type": "craft_metal_construction", "osm_id": "N2834606913", "lat": 58.3488915, "lon": 26.739239, "archetype": "Salariat" }, "geometry": { "type": "Point", "coordinates": [ 26.739239, 58.3488915 ] } },
{ "type": "Feature", "properties": { "building_type": "craft_caterer", "osm_id": "N7796373816", "lat": 58.3657567, "lon": 26.7192275, "archetype": "Salariat" }, "geometry": { "type": "Point", "coordinates": [ 26.7192275, 58.3657567 ] } },
{ "type": "Feature", "properties": { "building_type": "craft_hvac", "osm_id": "N12638842048", "lat": 58.3864645, "lon": 26.7269839, "archetype": "Salariat" }, "geometry": { "type": "Point", "coordinates": [ 26.7269839, 58.3864645 ] } }
]
}
